.gitignore
CHANGES.txt
LICENSE.txt
MANIFEST.in
README.txt
bootstrap.py
buildout.cfg
setup.py
js/__init__.py
js.angular_ui.egg-info/PKG-INFO
js.angular_ui.egg-info/SOURCES.txt
js.angular_ui.egg-info/dependency_links.txt
js.angular_ui.egg-info/entry_points.txt
js.angular_ui.egg-info/namespace_packages.txt
js.angular_ui.egg-info/not-zip-safe
js.angular_ui.egg-info/requires.txt
js.angular_ui.egg-info/top_level.txt
js/angular_ui/__init__.py
js/angular_ui/test_angularui.txt
js/angular_ui/resources/angular-ui-ieshiv.js
js/angular_ui/resources/angular-ui-ieshiv.min.js
js/angular_ui/resources/angular-ui.css
js/angular_ui/resources/angular-ui.js
js/angular_ui/resources/angular-ui.min.css
js/angular_ui/resources/angular-ui.min.js