Metadata-Version: 1.0
Name: js.angular-ui
Version: 0.4.0
Summary: Fanstatic packaging of AngularUI
Home-page: UNKNOWN
Author: UNKNOWN
Author-email: UNKNOWN
License: MIT
Platform: UNKNOWN
